goated/__init__.py
goated/example.py
goated/main.py
goated/version.py
goated/client/__init__.py
goated/client/base_client.py
goated/client/exceptions.py
goated/client/trading_client.py
goated/instructions/__init__.py
goated/instructions/cancel_order.py
goated/instructions/enums.py
goated/instructions/new_order.py
goated/instructions/reduce_order.py
goated/instructions/update_persistence.py
goated/state/__init__.py
goated/state/container.py
goated/state/market.py
goated/state/order.py
goated/state/pool.py
goated/state/position.py
goated/state/selection.py
goated/state/profiles/__init__.py
goated/state/profiles/current_liquidity_profile.py
goated/state/profiles/pool_profile.py
goated/state/profiles/position_profile.py
goated/state/profiles/target_liquidity_profile.py
goated/utils/__init__.py
goated/utils/bucketing.py
goated/utils/converter.py
goated/utils/encoder.py
goated/utils/payoff_signature.py
goated-0.0.7.dist-info/LICENSE.txt
goated-0.0.7.dist-info/METADATA
goated-0.0.7.dist-info/WHEEL
goated-0.0.7.dist-info/top_level.txt
goated-0.0.7.dist-info/RECORD
